koco_product_sqlmodel/__init__.py
koco_product_sqlmodel/dbmodels/DB-Tables.md
koco_product_sqlmodel/dbmodels/__init__.py
koco_product_sqlmodel/dbmodels/application.py
koco_product_sqlmodel/dbmodels/article.py
koco_product_sqlmodel/dbmodels/backlog.py
koco_product_sqlmodel/dbmodels/catalog.py
koco_product_sqlmodel/dbmodels/category_tree.py
koco_product_sqlmodel/dbmodels/changelog.py
koco_product_sqlmodel/dbmodels/definition.py
koco_product_sqlmodel/dbmodels/definition_reduced.py
koco_product_sqlmodel/dbmodels/family.py
koco_product_sqlmodel/dbmodels/filedata.py
koco_product_sqlmodel/dbmodels/models_enums.py
koco_product_sqlmodel/dbmodels/option.py
koco_product_sqlmodel/dbmodels/product_group.py
koco_product_sqlmodel/dbmodels/spectable.py
koco_product_sqlmodel/dbmodels/support.py
koco_product_sqlmodel/dbmodels/url.py
koco_product_sqlmodel/dbmodels/user.py
koco_product_sqlmodel/dbmodels/viewdef.py
koco_product_sqlmodel/dbmodels/sql/PHPMyAdmin_Snippets.sql
koco_product_sqlmodel/dbmodels/sql/add_column_description_json_in_cspectable.sql
koco_product_sqlmodel/dbmodels/sql/create_changelog_table_in_db.sql
koco_product_sqlmodel/dbmodels/sql/create_columns_order_prio_and_visibility_to_cfiledata.sql
koco_product_sqlmodel/dbmodels/sql/create_filedata_table_in_db.sql
koco_product_sqlmodel/dbmodels/sql/create_spectableitem_parent_view.sql
koco_product_sqlmodel/dbmodels/sql/create_viewdefs_in_db.sql
koco_product_sqlmodel/dbmodels/sql/resize_family_and_article_description.sql
koco_product_sqlmodel/fastapi/__init__.py
koco_product_sqlmodel/fastapi/kocoapi.py
koco_product_sqlmodel/fastapi/routes/__init__.py
koco_product_sqlmodel/fastapi/routes/application.py
koco_product_sqlmodel/fastapi/routes/article.py
koco_product_sqlmodel/fastapi/routes/catalog.py
koco_product_sqlmodel/fastapi/routes/categories.py
koco_product_sqlmodel/fastapi/routes/changelog.py
koco_product_sqlmodel/fastapi/routes/db_operations.py
koco_product_sqlmodel/fastapi/routes/family.py
koco_product_sqlmodel-0.1.38.dist-info/METADATA
koco_product_sqlmodel-0.1.38.dist-info/WHEEL
koco_product_sqlmodel-0.1.38.dist-info/licenses/LICENSE
koco_product_sqlmodel-0.1.38.dist-info/RECORD
