Metadata-Version: 2.3
Name: koco-product-sqlmodel
Version: 0.1.38
Summary: Python module containing the SQLMODEL for the KOCO MOTION product description in the catalog database. Used import into the flask project and the later to define API-project
Author-email: Gerrit Kocherscheidt <kochersg@koco-group.com>
Requires-Python: >=3.12
Requires-Dist: bcrypt==4.3.0
Requires-Dist: fastapi[standard]>=0.115.8
Requires-Dist: gunicorn>=23.0.0
Requires-Dist: mariadb>=1.1.10
Requires-Dist: openpyxl>=3.1.5
Requires-Dist: passlib[bcrypt]>=1.7.4
Requires-Dist: pillow>=11.1.0
Requires-Dist: pyjwt>=2.9.0
Requires-Dist: python-dotenv>=1.0.1
Requires-Dist: python-multipart>=0.0.20
Requires-Dist: sqlalchemy-utils>=0.41.2
Requires-Dist: sqlmodel>=0.0.22
